iflow_mcp_xhs_toolkit-1.2.2.dist-info/licenses/LICENSE
src/__init__.py
src/auth/__init__.py
src/auth/cookie_manager.py
src/auth/smart_auth_server.py
src/cli/__init__.py
src/cli/manual_commands.py
src/core/__init__.py
src/core/browser.py
src/core/config.py
src/core/exceptions.py
src/data/__init__.py
src/data/scheduler.py
src/data/storage_manager.py
src/data/storage/__init__.py
src/data/storage/base.py
src/data/storage/csv_storage.py
src/data/storage/pg_storage.py
src/server/__init__.py
src/server/mcp_server.py
src/tools/__init__.py
src/tools/manual_tools.py
src/utils/__init__.py
src/utils/image_processor.py
src/utils/logger.py
src/utils/text_utils.py
src/xiaohongshu/__init__.py
src/xiaohongshu/client.py
src/xiaohongshu/constants.py
src/xiaohongshu/interfaces.py
src/xiaohongshu/models.py
src/xiaohongshu/refactored_client.py
src/xiaohongshu/components/__init__.py
src/xiaohongshu/components/content_filler.py
src/xiaohongshu/components/data_collector.py
src/xiaohongshu/components/file_uploader.py
src/xiaohongshu/components/publisher.py
src/xiaohongshu/components/topic_automation.py
src/xiaohongshu/data_collector/__init__.py
src/xiaohongshu/data_collector/content_analysis.py
src/xiaohongshu/data_collector/dashboard.py
src/xiaohongshu/data_collector/fans.py
src/xiaohongshu/data_collector/utils.py
iflow_mcp_xhs_toolkit-1.2.2.dist-info/METADATA
iflow_mcp_xhs_toolkit-1.2.2.dist-info/WHEEL
iflow_mcp_xhs_toolkit-1.2.2.dist-info/entry_points.txt
iflow_mcp_xhs_toolkit-1.2.2.dist-info/top_level.txt
iflow_mcp_xhs_toolkit-1.2.2.dist-info/RECORD
