Metadata-Version: 2.4
Name: iflow-mcp_xhs-toolkit
Version: 1.2.2
Summary: 一个强大的小红书自动化工具包，支持通过MCP协议与AI客户端集成
Author: aki66938
License: MIT
Keywords: xiaohongshu,mcp,automation,ai,小红书
Classifier: Development Status :: 4 - Beta
Classifier: Intended Audience :: Developers
Classifier: License :: OSI Approved :: MIT License
Classifier: Programming Language :: Python :: 3
Classifier: Programming Language :: Python :: 3.10
Classifier: Programming Language :: Python :: 3.11
Classifier: Programming Language :: Python :: 3.12
Requires-Python: >=3.10
License-File: LICENSE
Requires-Dist: fastmcp>=2.0.0
Requires-Dist: requests>=2.31.0
Requires-Dist: aiohttp>=3.9.0
Requires-Dist: fastapi>=0.104.0
Requires-Dist: uvicorn>=0.24.0
Requires-Dist: selenium>=4.15.0
Requires-Dist: pydantic>=2.5.0
Requires-Dist: python-multipart>=0.0.6
Requires-Dist: pandas>=2.0.0
Requires-Dist: cryptography>=41.0.0
Requires-Dist: pycryptodome>=3.19.0
Requires-Dist: python-dotenv>=1.0.0
Requires-Dist: loguru>=0.7.2
Requires-Dist: apscheduler>=3.10.0
Provides-Extra: dev
Requires-Dist: pytest>=7.4.0; extra == "dev"
Requires-Dist: pytest-asyncio>=0.21.0; extra == "dev"
Requires-Dist: black>=23.0.0; extra == "dev"
Dynamic: license-file
